lightningnlp/__init__.py
lightningnlp/callbacks/__init__.py
lightningnlp/callbacks/early_stopping.py
lightningnlp/callbacks/ema.py
lightningnlp/callbacks/logger.py
lightningnlp/callbacks/model_checkpoint.py
lightningnlp/callbacks/swa.py
lightningnlp/callbacks/adversarial/__init__.py
lightningnlp/callbacks/adversarial/awp.py
lightningnlp/callbacks/adversarial/fgm.py
lightningnlp/callbacks/adversarial/freelb.py
lightningnlp/callbacks/adversarial/pgd.py
lightningnlp/callbacks/adversarial/vat.py
lightningnlp/core/__init__.py
lightningnlp/core/data.py
lightningnlp/core/finetuning.py
lightningnlp/core/iterable.py
lightningnlp/core/model.py
lightningnlp/core/predictor.py
lightningnlp/core/seq2seq/__init__.py
lightningnlp/core/seq2seq/data.py
lightningnlp/core/seq2seq/finetuning.py
lightningnlp/core/seq2seq/model.py
lightningnlp/core/seq2seq/utils.py
lightningnlp/data/__init__.py
lightningnlp/data/tokenizer.py
lightningnlp/data/vocab.py
lightningnlp/dataaug/__init__.py
lightningnlp/dataaug/base_augment.py
lightningnlp/dataaug/word_delete.py
lightningnlp/dataaug/word_insert.py
lightningnlp/dataaug/word_substitute.py
lightningnlp/dataaug/word_swap.py
lightningnlp/layers/__init__.py
lightningnlp/layers/activations.py
lightningnlp/layers/attentions.py
lightningnlp/layers/capsule.py
lightningnlp/layers/char.py
lightningnlp/layers/conv.py
lightningnlp/layers/crf.py
lightningnlp/layers/dropouts.py
lightningnlp/layers/embeddings.py
lightningnlp/layers/gate.py
lightningnlp/layers/global_pointer.py
lightningnlp/layers/layer_norm.py
lightningnlp/layers/lear.py
lightningnlp/layers/linears.py
lightningnlp/layers/mixout.py
lightningnlp/layers/mlp.py
lightningnlp/layers/pfn.py
lightningnlp/layers/pooling.py
lightningnlp/layers/position.py
lightningnlp/layers/set_decoder.py
lightningnlp/layers/transformer.py
lightningnlp/layers/utils.py
lightningnlp/losses/__init__.py
lightningnlp/losses/aslsinglelabel_loss.py
lightningnlp/losses/asymmetric_loss.py
lightningnlp/losses/contrastive_loss.py
lightningnlp-1.0.3.dist-info/LICENSE
lightningnlp-1.0.3.dist-info/METADATA
lightningnlp-1.0.3.dist-info/WHEEL
lightningnlp-1.0.3.dist-info/top_level.txt
lightningnlp-1.0.3.dist-info/RECORD
