Metadata-Version: 2.1
Name: lightningnlp
Version: 1.0.3
Summary: Pytorch-lightning Code Blocks for NLP
Home-page: https://github.com/xusenlinzy/lightningblocks
Author: xusenlin
Author-email: 1659821119@qq.com
License: MIT Licence
Platform: UNKNOWN
Requires-Python: >=3.7
License-File: LICENSE
Requires-Dist: colorama
Requires-Dist: colorlog
Requires-Dist: datasets
Requires-Dist: faster-tokenizer
Requires-Dist: jieba
Requires-Dist: onnx
Requires-Dist: onnxconverter-common
Requires-Dist: onnxruntime
Requires-Dist: pypinyin
Requires-Dist: pytorch-lightning
Requires-Dist: scikit-learn
Requires-Dist: scipy
Requires-Dist: seaborn
Requires-Dist: sentencepiece
Requires-Dist: setuptools
Requires-Dist: spacy
Requires-Dist: streamlit
Requires-Dist: torchmetrics
Requires-Dist: transformers
